climatePy/__init__.py
climatePy/_climatepy_filter.py
climatePy/_dap.py
climatePy/_extract_sites.py
climatePy/_netrc_utils.py
climatePy/_shortcuts.py
climatePy/_utils.py
climatePy/_viz.py
climatePy/data/catalog.parquet
tests/__init__.py
tests/test_climatepy_filter.py
tests/test_dap.py
tests/test_extract_sites.py
tests/test_netrc.py
tests/test_shortcuts.py
tests/test_utils.py
tests/test_vrt.py
climatePy-0.5.1.dist-info/LICENSE
climatePy-0.5.1.dist-info/METADATA
climatePy-0.5.1.dist-info/WHEEL
climatePy-0.5.1.dist-info/top_level.txt
climatePy-0.5.1.dist-info/RECORD
