Metadata-Version: 2.1
Name: climatePy
Version: 0.5.1
Summary: A Python package for getting point and gridded climate data by AOI.
Author: Angus Watters, Mike Johnson
Author-email: anguswatters@gmail.com, mikecp11@gmail.com
Classifier: Programming Language :: Python :: 3
Classifier: License :: OSI Approved :: GNU General Public License v3 or later (GPLv3+)
Classifier: Operating System :: OS Independent
Requires-Python: >=3.6
License-File: LICENSE
Requires-Dist: pandas
Requires-Dist: pyarrow
Requires-Dist: geopandas
Requires-Dist: shapely
Requires-Dist: pyproj
Requires-Dist: rasterio
Requires-Dist: xarray
Requires-Dist: rioxarray
Requires-Dist: rtree
Requires-Dist: numpy
Requires-Dist: geogif
Requires-Dist: netCDF4
Requires-Dist: joblib
